calculate_area/__init__.py
calculate_area/area_calculation.py
test/__init__.py
test/test_circl.py
test/test_triangle.py
library_calculate_area-0.0.2.dist-info/METADATA
library_calculate_area-0.0.2.dist-info/WHEEL
library_calculate_area-0.0.2.dist-info/top_level.txt
library_calculate_area-0.0.2.dist-info/RECORD
